promptim/__init__.py
promptim/__main__.py
promptim/_utils.py
promptim/config.py
promptim/py.typed
promptim/trainer.py
promptim/types.py
promptim/algorithms/__init__.py
promptim/algorithms/base.py
promptim/algorithms/minibatch.py
promptim/algorithms/mipro.py
promptim/algorithms/tpe_sampler.py
promptim/algorithms/phaseevo/__init__.py
promptim/algorithms/phaseevo/algo.py
promptim/algorithms/phaseevo/mutations.py
promptim/optimizers/__init__.py
promptim/optimizers/base.py
promptim/optimizers/debate.py
promptim/optimizers/feedback_guided.py
promptim/optimizers/fewshot.py
promptim/optimizers/metaprompt.py
promptim/tasks/__init__.py
promptim/tasks/metaprompt.py
promptim/tasks/scone.py
promptim/tasks/simpleqa.py
promptim/tasks/ticket_classification.py
promptim/tasks/tweet_generator.py
promptim-0.0.9.dist-info/METADATA
promptim-0.0.9.dist-info/WHEEL
promptim-0.0.9.dist-info/entry_points.txt
promptim-0.0.9.dist-info/licenses/LICENSE
promptim-0.0.9.dist-info/RECORD
