Metadata-Version: 2.4
Name: promptim
Version: 0.0.9
Summary: A framework for optimizing prompts through multi-task evaluation and iterative improvement
Author-email: William Fu-Hinthorn <13333726+hinthornw@users.noreply.github.com>
License-File: LICENSE
Requires-Python: >=3.11
Requires-Dist: click
Requires-Dist: langchain
Requires-Dist: langchain-anthropic>=0.3
Requires-Dist: langchain-openai>=0.3
Requires-Dist: langsmith>=0.2.11
Requires-Dist: pandas>=0.2.4
Requires-Dist: python-dotenv>=1.0.1
Requires-Dist: rich
Requires-Dist: trustcall>=0.0.28
